{"id":"index.html","dependencies":[{"name":"C:\\Users\\chengjinglu\\Desktop\\mvc-demo-1\\package.json","includedInParent":true,"mtime":1663037056924},{"name":"./main.js","dynamic":true,"parent":"C:\\Users\\chengjinglu\\Desktop\\mvc-demo-1\\src\\index.html","resolved":"C:\\Users\\chengjinglu\\Desktop\\mvc-demo-1\\src\\main.js"}],"generated":{"html":"<!DOCTYPE html>\r\n<html lang=\"en\">\r\n  <head>\r\n    <meta charset=\"UTF-8\">\r\n    <meta http-equiv=\"X-UA-Compatible\" content=\"IE=edge\">\r\n    <meta name=\"viewport\" content=\"width=device-width,initial-scale=1,minimum-scale=1,maximum-scale=1,user-scalable=no,viewport-fit=cover\">\r\n    <title>MVC Demo</title>\r\n  </head>\r\n  <body>\r\n    <div id=\"app1\">\r\n      <div class=\"output\">\r\n        <span>100</span>\r\n      </div>\r\n      <div class=\"actions\">\r\n        <button id=\"add1\">+1</button>\r\n        <button id=\"minus1\">-1</button>\r\n        <button id=\"mul2\">*2</button>\r\n        <button id=\"divide2\">รท2</button>\r\n      </div>\r\n    </div>\r\n    <div id=\"app2\"></div>\r\n    <div id=\"app3\"></div>\r\n    <div id=\"app4\"></div>\r\n    <script src=\"/23c0c206d13d5cb5764b223e5aabf928.js\"></script>\r\n  </body>\r\n</html>\r\n"},"hash":"7912b8829d51db918c813ed53f44ea07","cacheData":{}}